{
  "db_name": "PostgreSQL",
  "query": "\n        INSERT INTO incidents (id, title, description, service_name, status, severity, created_at, metadata)\n        VALUES ($1, $2, $3, $4, 'open', $5, $6, $7)\n        RETURNING id, title, description, service_name, status, severity,\n                  created_at, resolved_at, metadata\n        ",
  "describe": {
    "columns": [
      {
        "ordinal": 0,
        "name": "id",
        "type_info": "Uuid"
      },
      {
        "ordinal": 1,
        "name": "title",
        "type_info": "Varchar"
      },
      {
        "ordinal": 2,
        "name": "description",
        "type_info": "Text"
      },
      {
        "ordinal": 3,
        "name": "service_name",
        "type_info": "Varchar"
      },
      {
        "ordinal": 4,
        "name": "status",
        "type_info": "Varchar"
      },
      {
        "ordinal": 5,
        "name": "severity",
        "type_info": "Varchar"
      },
      {
        "ordinal": 6,
        "name": "created_at",
        "type_info": "Timestamptz"
      },
      {
        "ordinal": 7,
        "name": "resolved_at",
        "type_info": "Timestamptz"
      },
      {
        "ordinal": 8,
        "name": "metadata",
        "type_info": "Jsonb"
      }
    ],
    "parameters": {
      "Left": [
        "Uuid",
        "Varchar",
        "Text",
        "Varchar",
        "Varchar",
        "Timestamptz",
        "Jsonb"
      ]
    },
    "nullable": [
      false,
      false,
      true,
      false,
      false,
      false,
      false,
      true,
      true
    ]
  },
  "hash": "0b720ab0b3b3eddbf45d45c1d32d7f5b88ad670f7673fd59225fe47fd2c9f5a9"
}
